taxi_tempo
